fetch_fundamental_data/__init__.py
fetch_fundamental_data/cli.py
fetch_fundamental_data/company_data_extraction_EODH.py
fetch_fundamental_data/core.py
fetch_fundamental_data/data_analysis.py
fetch_fundamental_data-0.1.0.dist-info/licenses/LICENSE
fetch_fundamental_data-0.1.0.dist-info/METADATA
fetch_fundamental_data-0.1.0.dist-info/WHEEL
fetch_fundamental_data-0.1.0.dist-info/entry_points.txt
fetch_fundamental_data-0.1.0.dist-info/top_level.txt
fetch_fundamental_data-0.1.0.dist-info/RECORD
