Metadata-Version: 2.4
Name: fetch-fundamental-data
Version: 0.1.0
Summary: A Python package for fetching and analyzing fundamental financial data
Home-page: https://github.com/username/fetch-fundamental-data
Author: Carl Viggo Gravenhorst-Lövenstierne
Author-email: 
Maintainer: Carl Viggo Gravenhorst-Lövenstierne
License: MIT
Project-URL: Homepage, https://github.com/username/fetch-fundamental-data
Project-URL: Bug Reports, https://github.com/username/fetch-fundamental-data/issues
Project-URL: Source Code, https://github.com/username/fetch-fundamental-data
Project-URL: Documentation, https://github.com/username/fetch-fundamental-data/blob/main/README.md
Keywords: finance,stocks,fundamental analysis,financial data,EODHD
Classifier: Development Status :: 4 - Beta
Classifier: Intended Audience :: Financial and Insurance Industry
Classifier: Intended Audience :: Developers
Classifier: Topic :: Office/Business :: Financial :: Investment
Classifier: License :: OSI Approved :: MIT License
Classifier: Programming Language :: Python :: 3
Classifier: Programming Language :: Python :: 3.8
Classifier: Programming Language :: Python :: 3.9
Classifier: Programming Language :: Python :: 3.10
Classifier: Programming Language :: Python :: 3.11
Classifier: Programming Language :: Python :: 3.12
Requires-Python: >=3.8
License-File: LICENSE
Requires-Dist: requests>=2.25.0
Requires-Dist: pandas>=1.3.0
Requires-Dist: openpyxl>=3.0.0
Requires-Dist: numpy>=1.20.0
Dynamic: home-page
Dynamic: license-file
Dynamic: requires-python
